muesli/__init__.py
muesli/__version__.py
muesli-0.1.0.dist-info/METADATA
muesli-0.1.0.dist-info/RECORD
muesli-0.1.0.dist-info/WHEEL
muesli-0.1.0.dist-info/top_level.txt
